leveldbm.py
leveldict.py
setup.py
leveldict.egg-info/PKG-INFO
leveldict.egg-info/SOURCES.txt
leveldict.egg-info/dependency_links.txt
leveldict.egg-info/requires.txt
leveldict.egg-info/top_level.txt