Metadata-Version: 1.1
Name: leveldict
Version: 0.2
Summary: LevelDB dict-like wrappers.
Home-page: https://github.com/darkrho/leveldict
Author: Rolando Espinoza La fuente
Author-email: darkrho@gmail.com
License: BSD
Platform: UNKNOWN
Classifier: Programming Language :: Python
Classifier: Development Status :: 4 - Beta
Classifier: Intended Audience :: Developers
